Metadata-Version: 2.1
Name: gpiodev
Version: 0.0.1
Summary: Library to operate GPIO pins via character device
Home-page: https://github.com/bookwar/python-gpiodev
Author: Aleksandra Fedorova
Author-email: alpha@bookwar.info
License: Apache 2.0
Keywords: gpio,raspberry-pi
Platform: UNKNOWN
Classifier: Development Status :: 3 - Alpha
Classifier: Intended Audience :: Developers
Classifier: License :: OSI Approved :: Apache Software License
Classifier: Operating System :: POSIX :: Linux
Classifier: Programming Language :: Python
